rikihistory/__init__.py
rikihistory/history.py
rikihistory/rkhist.py
rikihistory/test_history.py
rikihistory-0.4.dist-info/METADATA
rikihistory-0.4.dist-info/WHEEL
rikihistory-0.4.dist-info/top_level.txt
rikihistory-0.4.dist-info/RECORD
