Metadata-Version: 2.1
Name: rikihistory
Version: 0.4
Summary: riki history page
Home-page: UNKNOWN
Author: John Besse
Author-email: bessej1@nku.edu
License: UNKNOWN
Platform: UNKNOWN
Requires-Python: >=3.7
